declaration/__init__.py
declaration/forms.py
declaration/middleware.py
declaration/urls.py
declaration/views.py
declaration/templates/declaration/_declaration_form.html
declaration/templates/declaration/declaration_form.html
declaration/templates/declaration/declaration_form_ajax.html
declaration/tests/__init__.py
declaration/tests/test_middleware.py
declaration/tests/test_views.py
django_declaration_middleware-0.1.0.dist-info/DESCRIPTION.rst
django_declaration_middleware-0.1.0.dist-info/METADATA
django_declaration_middleware-0.1.0.dist-info/RECORD
django_declaration_middleware-0.1.0.dist-info/WHEEL
django_declaration_middleware-0.1.0.dist-info/metadata.json
django_declaration_middleware-0.1.0.dist-info/top_level.txt
test_project/__init__.py
test_project/manage.py
test_project/settings.py
test_project/test_runner.py
test_project/urls.py
test_project/wsgi.py
